SLHPDataWarehousing/__init__.py
SLHPDataWarehousing/database_connector.py
SLHPDataWarehousing/environment_setup.py
SLHPDataWarehousing-0.3.0.dist-info/LICENSE
SLHPDataWarehousing-0.3.0.dist-info/METADATA
SLHPDataWarehousing-0.3.0.dist-info/WHEEL
SLHPDataWarehousing-0.3.0.dist-info/top_level.txt
SLHPDataWarehousing-0.3.0.dist-info/RECORD
