Metadata-Version: 2.1
Name: SLHPDataWarehousing
Version: 0.3.0
Summary: This package is used by the SLHP Data Warehousing Team for their day to day work
Author: Ben Fuqua
Author-email: fuquac@slhs.org
Classifier: Programming Language :: Python :: 3
Classifier: License :: OSI Approved :: MIT License
Classifier: Operating System :: OS Independent
Requires-Python: >=3.9
License-File: LICENSE
Requires-Dist: numpy
Requires-Dist: Flask
Requires-Dist: SQLAlchemy
Requires-Dist: WTForms
Requires-Dist: flask-wtf
Requires-Dist: wtforms-sqlalchemy
Requires-Dist: flask-sqlalchemy
Requires-Dist: databricks-sql-connector[sqlalchemy]
Requires-Dist: pyodbc
